odoo/addons/mass_mailing_unique/README.rst
odoo/addons/mass_mailing_unique/__init__.py
odoo/addons/mass_mailing_unique/__manifest__.py
odoo/addons/mass_mailing_unique/hooks.py
odoo/addons/mass_mailing_unique/i18n/ca.po
odoo/addons/mass_mailing_unique/i18n/de.po
odoo/addons/mass_mailing_unique/i18n/es.po
odoo/addons/mass_mailing_unique/i18n/fr.po
odoo/addons/mass_mailing_unique/i18n/hr.po
odoo/addons/mass_mailing_unique/i18n/it.po
odoo/addons/mass_mailing_unique/i18n/mass_mailing_unique.pot
odoo/addons/mass_mailing_unique/i18n/pt.po
odoo/addons/mass_mailing_unique/i18n/sl.po
odoo/addons/mass_mailing_unique/images/error-duplicated-email.png
odoo/addons/mass_mailing_unique/images/error-duplicated-list.png
odoo/addons/mass_mailing_unique/models/__init__.py
odoo/addons/mass_mailing_unique/models/mass_mailing.py
odoo/addons/mass_mailing_unique/readme/CONTRIBUTORS.rst
odoo/addons/mass_mailing_unique/readme/DESCRIPTION.rst
odoo/addons/mass_mailing_unique/readme/INSTALL.rst
odoo/addons/mass_mailing_unique/readme/USAGE.rst
odoo/addons/mass_mailing_unique/static/description/icon.png
odoo/addons/mass_mailing_unique/static/description/index.html
odoo/addons/mass_mailing_unique/tests/__init__.py
odoo/addons/mass_mailing_unique/tests/test_mass_mailing_unique.py
odoo11_addon_mass_mailing_unique-11.0.1.0.0.99.dev6.dist-info/METADATA
odoo11_addon_mass_mailing_unique-11.0.1.0.0.99.dev6.dist-info/WHEEL
odoo11_addon_mass_mailing_unique-11.0.1.0.0.99.dev6.dist-info/top_level.txt
odoo11_addon_mass_mailing_unique-11.0.1.0.0.99.dev6.dist-info/RECORD
